odoo/addons/uom_alias/README.rst
odoo/addons/uom_alias/__init__.py
odoo/addons/uom_alias/__manifest__.py
odoo/addons/uom_alias/i18n/it.po
odoo/addons/uom_alias/i18n/uom_alias.pot
odoo/addons/uom_alias/models/__init__.py
odoo/addons/uom_alias/models/uom_alias.py
odoo/addons/uom_alias/models/uom_uom.py
odoo/addons/uom_alias/readme/CONFIGURE.md
odoo/addons/uom_alias/readme/CONTRIBUTORS.md
odoo/addons/uom_alias/readme/DESCRIPTION.md
odoo/addons/uom_alias/readme/ROADMAP.md
odoo/addons/uom_alias/readme/USAGE.md
odoo/addons/uom_alias/security/ir.model.access.csv
odoo/addons/uom_alias/static/description/icon.png
odoo/addons/uom_alias/static/description/index.html
odoo/addons/uom_alias/static/img/screenshot-1.png
odoo/addons/uom_alias/tests/__init__.py
odoo/addons/uom_alias/tests/test_uom_alias.py
odoo/addons/uom_alias/views/uom_category.xml
odoo/addons/uom_alias/views/uom_uom.xml
odoo_addon_uom_alias-18.0.1.0.0.2.dist-info/METADATA
odoo_addon_uom_alias-18.0.1.0.0.2.dist-info/WHEEL
odoo_addon_uom_alias-18.0.1.0.0.2.dist-info/top_level.txt
odoo_addon_uom_alias-18.0.1.0.0.2.dist-info/RECORD
